nellie/__init__.py
nellie/cli.py
nellie/run copy.py
nellie/run.py
nellie/feature_extraction/__init__.py
nellie/feature_extraction/hierarchical.py
nellie/im_info/__init__.py
nellie/im_info/verifier.py
nellie/segmentation/__init__.py
nellie/segmentation/filtering.py
nellie/segmentation/labelling.py
nellie/segmentation/mocap_marking.py
nellie/segmentation/networking.py
nellie/tracking/__init__.py
nellie/tracking/all_tracks_for_label.py
nellie/tracking/flow_interpolation.py
nellie/tracking/flow_vector_viz.py
nellie/tracking/hu_tracking.py
nellie/tracking/voxel_reassignment.py
nellie/utils/__init__.py
nellie/utils/adaptive_run.py
nellie/utils/base_logger.py
nellie/utils/gpu_functions.py
nellie-1.0.3.dist-info/licenses/LICENSE
nellie_napari/__init__.py
nellie_napari/discover_plugins.py
nellie_napari/logo.png
nellie_napari/napari.yaml
nellie_napari/nellie_analysis.py
nellie_napari/nellie_fileselect.py
nellie_napari/nellie_home.py
nellie_napari/nellie_loader.py
nellie_napari/nellie_processor.py
nellie_napari/nellie_settings.py
nellie_napari/nellie_visualizer.py
pip-test/bin/activate_this.py
scripts/voxel_reassignment_demo.py
tests/test_hierarchical_aggregation.py
tests/test_hu_tracking.py
tests/test_labelling.py
tests/test_mocap_marking.py
tests/test_verifier_metadata.py
nellie-1.0.3.dist-info/METADATA
nellie-1.0.3.dist-info/WHEEL
nellie-1.0.3.dist-info/entry_points.txt
nellie-1.0.3.dist-info/top_level.txt
nellie-1.0.3.dist-info/RECORD
