Metadata-Version: 2.4
Name: nellie
Version: 1.0.3
Summary: Automated organelle segmentation, tracking, and hierarchical feature extraction in 2D/3D live-cell microscopy
Author-email: "Austin E. Y. T. Lefebvre" <austin.e.lefebvre+nellie@gmail.com>
Project-URL: Homepage, https://github.com/aelefebv/nellie
Classifier: Framework :: napari
Requires-Python: >=3.10
License-File: LICENSE
Requires-Dist: numpy
Requires-Dist: scipy
Requires-Dist: scikit-image
Requires-Dist: nd2
Requires-Dist: ome-types
Requires-Dist: pandas
Requires-Dist: matplotlib
Requires-Dist: napari[all]
Requires-Dist: imagecodecs
Provides-Extra: docs
Requires-Dist: mkdocs; extra == "docs"
Requires-Dist: mkdocs-material; extra == "docs"
Requires-Dist: mkdocstrings[python]; extra == "docs"
Dynamic: license-file
